error_solver/__init__.py
error_solver/_make_modules.py
error_solver/data/__init__.py
error_solver/data/_cylinder.py
error_solver/data/_wire_load.py
error_solver/data/area.ef
error_solver/data/cylinder.ef
error_solver/data/paths.py
error_solver/data/volume.ef
error_solver/data/wire_load.ef
error_solver/solvers/__init__.py
error_solver/solvers/_base_error_solver.py
error_solver/solvers/collector.py
error_solver/solvers/collector_test.py
error_solver/solvers/error_solver.py
error_solver/solvers/error_solver_py.py
error_solver/solvers/error_solver_py_test.py
error_solver/solvers/error_solver_test.py
error_solver/solvers/pipeline.py
error_solver/solvers/pipeline_test.py
error_solver-2.1.1.dist-info/LICENSE
error_solver-2.1.1.dist-info/METADATA
error_solver-2.1.1.dist-info/WHEEL
error_solver-2.1.1.dist-info/top_level.txt
error_solver-2.1.1.dist-info/RECORD
