Metadata-Version: 2.1
Name: error-solver
Version: 2.1.1
Summary: Estimates propagation error tolerances for systems of equations.
Home-page: https://github.com/mpewsey/error_solver
Author: Matt Pewsey
License: BSD 3-Clause License
Keywords: error-estimation,measurement-tolerances,error-tolerances
Platform: UNKNOWN
Classifier: Programming Language :: Python :: 3.5
Classifier: Programming Language :: Python :: 3.6
Classifier: Operating System :: OS Independent
Classifier: License :: OSI Approved :: BSD License
Requires-Python: >=3.5
Requires-Dist: numpy (>=1.14.5)
Requires-Dist: pandas (>=0.23.0)
Provides-Extra: all
Requires-Dist: sympy (>=1.1.1) ; extra == 'all'
Provides-Extra: docs
Requires-Dist: docutils (==0.14) ; extra == 'docs'
Requires-Dist: numpydoc (>=0.8.0) ; extra == 'docs'
Provides-Extra: test
Requires-Dist: pytest (>=3.5.1) ; extra == 'test'
Requires-Dist: pytest-cov (>=2.5.1) ; extra == 'test'
Requires-Dist: codecov (>=2.0.15) ; extra == 'test'
Requires-Dist: sympy (>=1.1.1) ; extra == 'test'
